modules/control.v
// Rsic 16 control unit

module control(
    input [2:0] op,
    input       EQ,
    
    output reg [1:0] FUNC_alu, // AND, NAND, PASS1, EQL
    output reg       MUX_alu1,
    output reg       MUX_alu2,
    output reg [1:0] MUX_pc,
    output reg       MUX_rf,
    output reg [1:0] MUX_tgt,
    output reg       WE_rf,
    output reg       WE_dmem
    );

    // Parameters for opcodes
    parameter ADD  = 3'b000;
    parameter ADDI = 3'b001;
    parameter NAND = 3'b010;
    parameter LUI  = 3'b011;
    parameter LW   = 3'b100;
    parameter SW   = 3'b101;
    parameter BEQ  = 3'b110;
    parameter JALR = 3'b111;

    always @(*) begin
        // Default values for all control signals
        FUNC_alu = 2'b00; // ADD
        MUX_alu1 = 1'b0; // Src1
        MUX_alu2 = 1'b0; // Src2
        MUX_pc   = 2'b00; // pc + 1
        MUX_rf   = 1'b0;  // rC
        MUX_tgt  = 2'b00; // data memory
        WE_rf    = 1'b0; // disable reg file
        WE_dmem  = 1'b0; // disable data memory


        // Set control signals based on opcode
        case(op)
            ADD: begin // ADD
                FUNC_alu = 2'b00; 
                MUX_alu1 = 1'b0;
                MUX_alu2 = 1'b0;
                MUX_pc   = 2'b00;
                MUX_rf   = 1'b0;
                MUX_tgt  = 2'b01; 
                WE_rf    = 1'b1;
                WE_dmem  = 1'b0;
            end
            ADDI: begin // ADDI
                FUNC_alu = 2'b00; 
                MUX_alu1 = 1'b0;
                MUX_alu2 = 1'b1; 
                MUX_pc   = 2'b00;
                MUX_rf   = 1'b0;
                MUX_tgt  = 2'b01; 
                WE_rf    = 1'b1;
                WE_dmem  = 1'b0;
            end
            NAND: begin // NAND
                FUNC_alu = 2'b01; 
                MUX_alu1 = 1'b0;
                MUX_alu2 = 1'b0; 
                MUX_pc   = 2'b00;
                MUX_rf   = 1'b0;
                MUX_tgt  = 2'b01; 
                WE_rf    = 1'b1;
                WE_dmem  = 1'b0;
            end
            LUI: begin // LUI
                FUNC_alu = 2'b10; 
                MUX_alu1 = 1'b1; 
                MUX_alu2 = 1'b0; 
                MUX_pc   = 2'b00;
                MUX_rf   = 1'b0;
                MUX_tgt  = 2'b01; 
                WE_rf    = 1'b1;
                WE_dmem  = 1'b0;
            end
            LW: begin // LW
                FUNC_alu = 2'b00; 
                MUX_alu1 = 1'b0;
                MUX_alu2 = 1'b1; 
                MUX_pc   = 2'b00;
                MUX_rf   = 1'b0; 
                MUX_tgt  = 2'b00; 
                WE_rf    = 1'b1;
                WE_dmem  = 1'b0;
            end
            SW: begin // SW
                FUNC_alu = 2'b00; 
                MUX_alu1 = 1'b0;
                MUX_alu2 = 1'b1; 
                MUX_pc   = 2'b00;
                MUX_rf   = 1'b1; 
                MUX_tgt  = 2'b00; 
                WE_rf    = 1'b0;
                WE_dmem  = 1'b1;
            end
            BEQ: begin // BEQ
                FUNC_alu = 2'b11; 
                MUX_alu1 = 1'b0;
                MUX_alu2 = 1'b0; 
                MUX_pc   = EQ ? 2'b01 : 2'b00; 
                MUX_rf   = 1'b1;
                MUX_tgt  = 2'b00; 
                WE_rf    = 1'b0;
                WE_dmem  = 1'b0;
            end
            JALR: begin // JALR
                FUNC_alu = 2'b10; 
                MUX_alu1 = 1'b0;
                MUX_alu2 = 1'b0; 
                MUX_pc   = 2'b10; 
                MUX_rf   = 1'b0;
                MUX_tgt  = 2'b10; 
                WE_rf    = 1'b1;
                WE_dmem  = 1'b0;
            end
        endcase
    end


endmodule

control/control_tb.v
`timescale 1ns / 1ps

module control_tb;

    // Inputs to DUT
    reg [2:0] op;
    reg       EQ;

    // Outputs from DUT
    wire [1:0] FUNC_alu;
    wire       MUX_alu1;
    wire       MUX_alu2;
    wire [1:0] MUX_pc;
    wire       MUX_rf;
    wire [1:0] MUX_tgt;
    wire       WE_rf;
    wire       WE_dmem;

    // Instantiate the DUT
    control uut (
        .op(op),
        .EQ(EQ),
        .FUNC_alu(FUNC_alu),
        .MUX_alu1(MUX_alu1),
        .MUX_alu2(MUX_alu2),
        .MUX_pc(MUX_pc),
        .MUX_rf(MUX_rf),
        .MUX_tgt(MUX_tgt),
        .WE_rf(WE_rf),
        .WE_dmem(WE_dmem)
    );

    // Parameters for opcodes
    parameter ADD  = 3'b000;
    parameter ADDI = 3'b001;
    parameter NAND = 3'b010;
    parameter LUI  = 3'b011;
    parameter LW   = 3'b100;
    parameter SW   = 3'b101;
    parameter BEQ  = 3'b110;
    parameter JALR = 3'b111;
    
    // Test stimulus
    initial begin
        // Setup waveform dumping
        $dumpfile("control_tb.vcd");
        $dumpvars(0, control_tb);
        
        // Monitor for any changes to inputs or outputs
        $monitor("Time=%0t op=%b EQ=%b | FUNC_alu=%b, MUX_alu1=%b, MUX_alu2=%b, MUX_pc=%b, MUX_rf=%b, MUX_tgt=%b, WE_rf=%b, WE_dmem=%b",
                 $time, op, EQ, FUNC_alu, MUX_alu1, MUX_alu2, MUX_pc, MUX_rf, MUX_tgt, WE_rf, WE_dmem);

        // Initialize inputs
        op = 3'b000;
        EQ = 1'b0;
        #10; // Wait for logic to settle

        // --- Test ADD ---
        op = ADD;
        EQ = 1'b0; // EQ doesn't matter for ADD
        #10;
        check_outputs(2'b00, 1'b0, 1'b0, 2'b00, 1'b0, 2'b01, 1'b1, 1'b0);

        // --- Test ADDI ---
        op = ADDI;
        #10;
        check_outputs(2'b00, 1'b0, 1'b1, 2'b00, 1'b0, 2'b01, 1'b1, 1'b0);

        // --- Test NAND ---
        op = NAND;
        #10;
        check_outputs(2'b01, 1'b0, 1'b0, 2'b00, 1'b0, 2'b01, 1'b1, 1'b0);

        // --- Test LUI ---
        op = LUI;
        #10;
        check_outputs(2'b10, 1'b1, 1'b0, 2'b00, 1'b0, 2'b01, 1'b1, 1'b0);

        // --- Test LW ---
        op = LW;
        #10;
        check_outputs(2'b00, 1'b0, 1'b1, 2'b00, 1'b0, 2'b00, 1'b1, 1'b0);

        // --- Test SW ---
        op = SW;
        #10;
        check_outputs(2'b00, 1'b0, 1'b1, 2'b00, 1'b1, 2'b00, 1'b0, 1'b1);

        // --- Test BEQ (EQ = 0) ---
        op = BEQ;
        EQ = 1'b0; // Branch NOT taken
        #10;
        check_outputs(2'b11, 1'b0, 1'b0, 2'b00, 1'b1, 2'b00, 1'b0, 1'b0);

        // --- Test BEQ (EQ = 1) ---
        op = BEQ;
        EQ = 1'b1; // Branch IS taken
        #10;
        check_outputs(2'b11, 1'b0, 1'b0, 2'b01, 1'b1, 2'b00, 1'b0, 1'b0);

        // --- Test JALR ---
        op = JALR;
        EQ = 1'b0; // EQ doesn't matter
        #10;
        check_outputs(2'b10, 1'b0, 1'b0, 2'b10, 1'b0, 2'b10, 1'b1, 1'b0);
        
        #10;
        $display("--- All test cases finished ---");
        $finish; // End simulation
    end

    // Task to check all outputs against expected values
    task check_outputs;
        input [1:0] exp_FUNC_alu;
        input       exp_MUX_alu1;
        input       exp_MUX_alu2;
        input [1:0] exp_MUX_pc;
        input       exp_MUX_rf;
        input [1:0] exp_MUX_tgt;
        input       exp_WE_rf;
        input       exp_WE_dmem;
        
        begin
            if (FUNC_alu !== exp_FUNC_alu || MUX_alu1 !== exp_MUX_alu1 || MUX_alu2 !== exp_MUX_alu2 ||
                MUX_pc !== exp_MUX_pc || MUX_rf !== exp_MUX_rf || MUX_tgt !== exp_MUX_tgt ||
                WE_rf !== exp_WE_rf || WE_dmem !== exp_WE_dmem) 
            begin
                $display("\n!!!!!!!!!!!!!!!!!!!!!!!!!!!!!!!!!!!!!!!!!!!!!!!!!!!!!!!!!!!!!!!!!!");
                $display("ERROR @ time %0t: op=%b, EQ=%b", $time, op, EQ);
                $display("  Expected: FUNC_alu=%b, MUX_alu1=%b, MUX_alu2=%b, MUX_pc=%b, MUX_rf=%b, MUX_tgt=%b, WE_rf=%b, WE_dmem=%b",
                         exp_FUNC_alu, exp_MUX_alu1, exp_MUX_alu2, exp_MUX_pc, exp_MUX_rf, exp_MUX_tgt, exp_WE_rf, exp_WE_dmem);
                $display("  Actual:   FUNC_alu=%b, MUX_alu1=%b, MUX_alu2=%b, MUX_pc=%b, MUX_rf=%b, MUX_tgt=%b, WE_rf=%b, WE_dmem=%b",
                         FUNC_alu, MUX_alu1, MUX_alu2, MUX_pc, MUX_rf, MUX_tgt, WE_rf, WE_dmem);
                $display("!!!!!!!!!!!!!!!!!!!!!!!!!!!!!!!!!!!!!!!!!!!!!!!!!!!!!!!!!!!!!!!!!!\n");
            end 
            else begin
                $display("SUCCESS @ time %0t: op=%b, EQ=%b -> All outputs correct.", $time, op, EQ);
            end
        end
    endtask

endmodule

control_tb.vcd
$date
	Tue Oct 28 21:10:49 2025
$end
$version
	Icarus Verilog
$end
$timescale
	1ps
$end
$scope module control_tb $end
$var wire 1 ! WE_rf $end
$var wire 1 " WE_dmem $end
$var wire 2 # MUX_tgt [1:0] $end
$var wire 1 $ MUX_rf $end
$var wire 2 % MUX_pc [1:0] $end
$var wire 1 & MUX_alu2 $end
$var wire 1 ' MUX_alu1 $end
$var wire 2 ( FUNC_alu [1:0] $end
$var parameter 3 ) ADD $end
$var parameter 3 * ADDI $end
$var parameter 3 + BEQ $end
$var parameter 3 , JALR $end
$var parameter 3 - LUI $end
$var parameter 3 . LW $end
$var parameter 3 / NAND $end
$var parameter 3 0 SW $end
$var reg 1 1 EQ $end
$var reg 3 2 op [2:0] $end
$scope module uut $end
$var wire 1 1 EQ $end
$var wire 3 3 op [2:0] $end
$var parameter 3 4 ADD $end
$var parameter 3 5 ADDI $end
$var parameter 3 6 BEQ $end
$var parameter 3 7 JALR $end
$var parameter 3 8 LUI $end
$var parameter 3 9 LW $end
$var parameter 3 : NAND $end
$var parameter 3 ; SW $end
$var reg 2 < FUNC_alu [1:0] $end
$var reg 1 ' MUX_alu1 $end
$var reg 1 & MUX_alu2 $end
$var reg 2 = MUX_pc [1:0] $end
$var reg 1 $ MUX_rf $end
$var reg 2 > MUX_tgt [1:0] $end
$var reg 1 " WE_dmem $end
$var reg 1 ! WE_rf $end
$upscope $end
$scope task check_outputs $end
$var reg 2 ? exp_FUNC_alu [1:0] $end
$var reg 1 @ exp_MUX_alu1 $end
$var reg 1 A exp_MUX_alu2 $end
$var reg 2 B exp_MUX_pc [1:0] $end
$var reg 1 C exp_MUX_rf $end
$var reg 2 D exp_MUX_tgt [1:0] $end
$var reg 1 E exp_WE_dmem $end
$var reg 1 F exp_WE_rf $end
$upscope $end
$upscope $end
$enddefinitions $end
$comment Show the parameter values. $end
$dumpall
b101 ;
b10 :
b100 9
b11 8
b111 7
b110 6
b1 5
b0 4
b101 0
b10 /
b100 .
b11 -
b111 ,
b110 +
b1 *
b0 )
$end
#0
$dumpvars
xF
xE
bx D
xC
bx B
xA
x@
bx ?
b1 >
b0 =
b0 <
b0 3
b0 2
01
b0 (
0'
0&
b0 %
0$
b1 #
0"
1!
$end
#20000
1&
1!
b1 #
b1 >
b1 2
b1 3
0E
1F
b1 D
0C
b0 B
0A
0@
b0 ?
#30000
b1 (
b1 <
1!
b1 #
b1 >
0&
b10 2
b10 3
1A
#40000
1'
1!
b1 #
b1 >
b10 (
b10 <
b11 2
b11 3
0A
b1 ?
#50000
1&
1!
b0 #
b0 >
0'
b0 (
b0 <
b100 2
b100 3
1@
b10 ?
#60000
1"
1$
0!
1&
b101 2
b101 3
b0 D
1A
0@
b0 ?
#70000
b11 (
b11 <
0"
1$
0&
b110 2
b110 3
1E
0F
1C
#80000
b1 %
b1 =
1$
b11 (
b11 <
11
0E
0A
b11 ?
#90000
1!
b10 #
b10 >
0$
b10 %
b10 =
b10 (
b10 <
01
b111 2
b111 3
b1 B
#100000
1F
b10 D
0C
b10 B
b10 ?
